<?xml version='1.0' encoding='iso-8859-1'?>
<BMP>
  <agente>
    <codigo_empresa>0408</codigo_empresa>
    <ano>2024</ano>
    <mes>11</mes>
  </agente>
  <contas><conta>
      <numero>1101102</numero>
      <debito>4734522,52</debito>
      <credito>4734322,67</credito>
      <saldo>1884,11</saldo>
    </conta>
    <conta>
      <numero>11012</numero>
      <debito>5315893,39</debito>
      <credito>4463947,69</credito>
      <saldo>7869814,99</saldo>
    </conta>
    <conta>
      <numero>1103101</numero>
      <debito>9941199,25</debito>
      <credito>10505134,10</credito>
      <saldo>5423629,67</saldo>
    </conta>
    <conta>
      <numero>11071</numero>
      <debito>60216,96</debito>
      <credito>209260,80</credito>
      <saldo>543052,50</saldo>
    </conta>
    <conta>
      <numero>11122</numero>
      <debito>0,00</debito>
      <credito>30448,70</credito>
      <saldo>194824,62</saldo>
    </conta>
    <conta>
      <numero>1119102</numero>
      <debito>141435,88</debito>
      <credito>128634,00</credito>
      <saldo>120887,13</saldo>
    </conta>
    <conta>
      <numero>1206101</numero>
      <debito>0,00</debito>
      <credito>0,00</credito>
      <saldo>353594,12</saldo>
    </conta>
    <conta>
      <numero>12091</numero>
      <debito>42096,36</debito>
      <credito>0,00</credito>
      <saldo>187616843,81</saldo>
    </conta>
    <conta>
      <numero>12121</numero>
      <debito>181153,68</debito>
      <credito>15096,14</credito>
      <saldo>243543,76</saldo>
    </conta>
    <conta>
      <numero>122020101</numero>
      <debito>1796,72</debito>
      <credito>20382,50</credito>
      <saldo>19494144,82</saldo>
    </conta>
    <conta>
      <numero>123210101</numero>
      <debito>0,00</debito>
      <credito>0,00</credito>
      <saldo>40000,00</saldo>
    </conta>
    <conta>
      <numero>123210102</numero>
      <debito>0,00</debito>
      <credito>0,00</credito>
      <saldo>180129097,16</saldo>
    </conta>
    <conta>
      <numero>123210103</numero>
      <debito>0,00</debito>
      <credito>0,00</credito>
      <saldo>271466988,38</saldo>
    </conta>
    <conta>
      <numero>123210104</numero>
      <debito>0,00</debito>
      <credito>0,00</credito>
      <saldo>186540925,09</saldo>
    </conta>
    <conta>
      <numero>123210105</numero>
      <debito>0,00</debito>
      <credito>0,00</credito>
      <saldo>555097,48</saldo>
    </conta>
    <conta>
      <numero>123210106</numero>
      <debito>0,00</debito>
      <credito>0,00</credito>
      <saldo>357912,22</saldo>
    </conta>
    <conta>
      <numero>123210201</numero>
      <debito>0,00</debito>
      <credito>0,00</credito>
      <saldo>24000,00</saldo>
    </conta>
    <conta>
      <numero>123210202</numero>
      <debito>0,00</debito>
      <credito>515644,25</credito>
      <saldo>-77760091,90</saldo>
    </conta>
    <conta>
      <numero>123210203</numero>
      <debito>0,00</debito>
      <credito>450412,82</credito>
      <saldo>-67278240,88</saldo>
    </conta>
    <conta>
      <numero>123210204</numero>
      <debito>0,00</debito>
      <credito>385186,79</credito>
      <saldo>-62331392,77</saldo>
    </conta>
    <conta>
      <numero>123210205</numero>
      <debito>0,00</debito>
      <credito>2102,01</credito>
      <saldo>-487380,12</saldo>
    </conta>
    <conta>
      <numero>123210206</numero>
      <debito>0,00</debito>
      <credito>1042,36</credito>
      <saldo>-159520,19</saldo>
    </conta>
    <conta>
      <numero>123210399</numero>
      <debito>0,00</debito>
      <credito>0,00</credito>
      <saldo>-2168694,72</saldo>
    </conta>
    <conta>
      <numero>1232170</numero>
      <debito>0,00</debito>
      <credito>0,00</credito>
      <saldo>105249389,41</saldo>
    </conta>
    <conta>
      <numero>123240104</numero>
      <debito>0,00</debito>
      <credito>0,00</credito>
      <saldo>408955,87</saldo>
    </conta>
    <conta>
      <numero>123240106</numero>
      <debito>0,00</debito>
      <credito>0,00</credito>
      <saldo>310718,20</saldo>
    </conta>
    <conta>
      <numero>123240204</numero>
      <debito>0,00</debito>
      <credito>3883,79</credito>
      <saldo>-185584,44</saldo>
    </conta>
    <conta>
      <numero>123240206</numero>
      <debito>0,00</debito>
      <credito>1593,27</credito>
      <saldo>-311520,54</saldo>
    </conta>
    <conta>
      <numero>123310103</numero>
      <debito>0,00</debito>
      <credito>0,00</credito>
      <saldo>580891,27</saldo>
    </conta>
    <conta>
      <numero>123310203</numero>
      <debito>0,00</debito>
      <credito>827,58</credito>
      <saldo>-226053,77</saldo>
    </conta>
    <conta>
      <numero>21013</numero>
      <debito>1400690,43</debito>
      <credito>1102019,26</credito>
      <saldo>-1124051,79</saldo>
    </conta>
    <conta>
      <numero>210210101</numero>
      <debito>0,00</debito>
      <credito>0,00</credito>
      <saldo>217375550,07</saldo>
    </conta>
    <conta>
      <numero>2102301</numero>
      <debito>15096,14</debito>
      <credito>181153,68</credito>
      <saldo>-167265,08</saldo>
    </conta>
    <conta>
      <numero>2103101</numero>
      <debito>314186,08</debito>
      <credito>326931,28</credito>
      <saldo>-229670,08</saldo>
    </conta>
    <conta>
      <numero>2103102</numero>
      <debito>250965,40</debito>
      <credito>158230,50</credito>
      <saldo>-248552,63</saldo>
    </conta>
    <conta>
      <numero>2103103</numero>
      <debito>40550,64</debito>
      <credito>36073,43</credito>
      <saldo>-382799,60</saldo>
    </conta>
    <conta>
      <numero>2105101</numero>
      <debito>68240,49</debito>
      <credito>176881,43</credito>
      <saldo>-333280,45</saldo>
    </conta>
    <conta>
      <numero>2105102</numero>
      <debito>0,00</debito>
      <credito>46592,01</credito>
      <saldo>-132334,14</saldo>
    </conta>
    <conta>
      <numero>2105103</numero>
      <debito>25820,58</debito>
      <credito>28041,49</credito>
      <saldo>-70471,68</saldo>
    </conta>
    <conta>
      <numero>2105104</numero>
      <debito>134262,99</debito>
      <credito>129422,26</credito>
      <saldo>-391970,75</saldo>
    </conta>
    <conta>
      <numero>2105201</numero>
      <debito>93183,61</debito>
      <credito>93183,61</credito>
      <saldo>0,00</saldo>
    </conta>
    <conta>
      <numero>2105301</numero>
      <debito>16768,31</debito>
      <credito>2811,26</credito>
      <saldo>-86849,80</saldo>
    </conta>
    <conta>
      <numero>2105501</numero>
      <debito>184373,27</debito>
      <credito>378623,49</credito>
      <saldo>-785558,15</saldo>
    </conta>
    <conta>
      <numero>2105502</numero>
      <debito>39112,08</debito>
      <credito>49187,61</credito>
      <saldo>-45277,62</saldo>
    </conta>
    <conta>
      <numero>21058</numero>
      <debito>86213,45</debito>
      <credito>0,00</credito>
      <saldo>-47652,27</saldo>
    </conta>
    <conta>
      <numero>2108101</numero>
      <debito>12032,58</debito>
      <credito>257628,65</credito>
      <saldo>-2664535,95</saldo>
    </conta>
    <conta>
      <numero>2108102</numero>
      <debito>6016,29</debito>
      <credito>128579,98</credito>
      <saldo>-1329741,00</saldo>
    </conta>
    <conta>
      <numero>210810301</numero>
      <debito>541288,41</debito>
      <credito>1623674,33</credito>
      <saldo>-2426801,70</saldo>
    </conta>
    <conta>
      <numero>2108199</numero>
      <debito>0,00</debito>
      <credito>0,00</credito>
      <saldo>-1798317,58</saldo>
    </conta>
    <conta>
      <numero>21083</numero>
      <debito>109745,58</debito>
      <credito>129422,26</credito>
      <saldo>-633396,93</saldo>
    </conta>
    <conta>
      <numero>21087</numero>
      <debito>90592,69</debito>
      <credito>141651,65</credito>
      <saldo>-252095,57</saldo>
    </conta>
    <conta>
      <numero>2108999</numero>
      <debito>589544,28</debito>
      <credito>589544,28</credito>
      <saldo>0,00</saldo>
    </conta>
    <conta>
      <numero>22013</numero>
      <debito>109301,43</debito>
      <credito>0,00</credito>
      <saldo>-45322027,39</saldo>
    </conta>
    <conta>
      <numero>2202301</numero>
      <debito>0,00</debito>
      <credito>0,00</credito>
      <saldo>81969,05</saldo>
    </conta>
    <conta>
      <numero>22058</numero>
      <debito>0,00</debito>
      <credito>0,00</credito>
      <saldo>-2702257,20</saldo>
    </conta>
    <conta>
      <numero>22062</numero>
      <debito>0,00</debito>
      <credito>0,00</credito>
      <saldo>-3980796,46</saldo>
    </conta>
    <conta>
      <numero>2210101</numero>
      <debito>0,00</debito>
      <credito>0,00</credito>
      <saldo>-9518802,63</saldo>
    </conta>
    <conta>
      <numero>2210201</numero>
      <debito>0,00</debito>
      <credito>0,00</credito>
      <saldo>-3399010,94</saldo>
    </conta>
    <conta>
      <numero>2211299</numero>
      <debito>1180903,68</debito>
      <credito>1466232,44</credito>
      <saldo>-55799913,46</saldo>
    </conta>
    <conta>
      <numero>222310101</numero>
      <debito>2582978,00</debito>
      <credito>0,00</credito>
      <saldo>-235193468,66</saldo>
    </conta>
    <conta>
      <numero>24011</numero>
      <debito>0,00</debito>
      <credito>0,00</credito>
      <saldo>-92000000,00</saldo>
    </conta>
    <conta>
      <numero>24062</numero>
      <debito>0,00</debito>
      <credito>0,00</credito>
      <saldo>427148733,68</saldo>
    </conta>
    <conta>
      <numero>610110102</numero>
      <debito>129422,26</debito>
      <credito>4322585,26</credito>
      <saldo>-28637866,31</saldo>
    </conta>
    <conta>
      <numero>610113001</numero>
      <debito>28041,49</debito>
      <credito>0,00</credito>
      <saldo>208763,62</saldo>
    </conta>
    <conta>
      <numero>610113101</numero>
      <debito>33087,73</debito>
      <credito>0,00</credito>
      <saldo>189494,64</saldo>
    </conta>
    <conta>
      <numero>610113103</numero>
      <debito>129422,26</debito>
      <credito>0,00</credito>
      <saldo>865348,15</saldo>
    </conta>
    <conta>
      <numero>610113105</numero>
      <debito>0,00</debito>
      <credito>0,00</credito>
      <saldo>61203,15</saldo>
    </conta>
    <conta>
      <numero>610113109</numero>
      <debito>141651,65</debito>
      <credito>0,00</credito>
      <saldo>1646369,69</saldo>
    </conta>
    <conta>
      <numero>610113199</numero>
      <debito>589544,28</debito>
      <credito>0,00</credito>
      <saldo>6681060,87</saldo>
    </conta>
    <conta>
      <numero>610510501</numero>
      <debito>560632,39</debito>
      <credito>130359,31</credito>
      <saldo>5061560,62</saldo>
    </conta>
    <conta>
      <numero>610510502</numero>
      <debito>375983,30</debito>
      <credito>0,00</credito>
      <saldo>2144711,26</saldo>
    </conta>
    <conta>
      <numero>610510508</numero>
      <debito>25933,22</debito>
      <credito>25983,25</credito>
      <saldo>1351349,72</saldo>
    </conta>
    <conta>
      <numero>610510599</numero>
      <debito>-240,17</debito>
      <credito>0,00</credito>
      <saldo>-5419,00</saldo>
    </conta>
    <conta>
      <numero>610510701</numero>
      <debito>347413,40</debito>
      <credito>0,00</credito>
      <saldo>3159314,51</saldo>
    </conta>
    <conta>
      <numero>610510801</numero>
      <debito>260546,24</debito>
      <credito>0,00</credito>
      <saldo>6849598,40</saldo>
    </conta>
    <conta>
      <numero>610510901</numero>
      <debito>73009,00</debito>
      <credito>0,00</credito>
      <saldo>1036790,08</saldo>
    </conta>
    <conta>
      <numero>610510902</numero>
      <debito>776296,97</debito>
      <credito>0,00</credito>
      <saldo>8570106,84</saldo>
    </conta>
    <conta>
      <numero>610511001</numero>
      <debito>33042,06</debito>
      <credito>0,00</credito>
      <saldo>338229,39</saldo>
    </conta>
    <conta>
      <numero>610511601</numero>
      <debito>93183,61</debito>
      <credito>0,00</credito>
      <saldo>575359,78</saldo>
    </conta>
    <conta>
      <numero>610511701</numero>
      <debito>1375585,57</debito>
      <credito>2582978,00</credito>
      <saldo>-13307227,98</saldo>
    </conta>
    <conta>
      <numero>610521801</numero>
      <debito>12,74</debito>
      <credito>0,00</credito>
      <saldo>50,96</saldo>
    </conta>
    <conta>
      <numero>610540501</numero>
      <debito>17882,36</debito>
      <credito>15,78</credito>
      <saldo>211008,86</saldo>
    </conta>
    <conta>
      <numero>610540502</numero>
      <debito>11986,47</debito>
      <credito>0,00</credito>
      <saldo>170612,04</saldo>
    </conta>
    <conta>
      <numero>610540508</numero>
      <debito>24220,36</debito>
      <credito>1569,09</credito>
      <saldo>318155,32</saldo>
    </conta>
    <conta>
      <numero>610540601</numero>
      <debito>28369,96</debito>
      <credito>0,00</credito>
      <saldo>312447,34</saldo>
    </conta>
    <conta>
      <numero>610540701</numero>
      <debito>13282,05</debito>
      <credito>0,00</credito>
      <saldo>156201,32</saldo>
    </conta>
    <conta>
      <numero>610540801</numero>
      <debito>268456,13</debito>
      <credito>0,00</credito>
      <saldo>7046537,47</saldo>
    </conta>
    <conta>
      <numero>610540901</numero>
      <debito>1200,00</debito>
      <credito>0,00</credito>
      <saldo>11244,98</saldo>
    </conta>
    <conta>
      <numero>610541701</numero>
      <debito>5477,06</debito>
      <credito>0,00</credito>
      <saldo>39925,84</saldo>
    </conta>
    <conta>
      <numero>610541801</numero>
      <debito>15096,14</debito>
      <credito>0,00</credito>
      <saldo>140031,15</saldo>
    </conta>
    <conta>
      <numero>611112199</numero>
      <debito>209260,80</debito>
      <credito>567820,60</credito>
      <saldo>-4592980,37</saldo>
    </conta>
    <conta>
      <numero>611112201</numero>
      <debito>567820,60</debito>
      <credito>569820,60</credito>
      <saldo>-404426,47</saldo>
    </conta>
    <conta>
      <numero>611113001</numero>
      <debito>0,00</debito>
      <credito>0,00</credito>
      <saldo>17012,94</saldo>
    </conta>
    <conta>
      <numero>611113002</numero>
      <debito>0,00</debito>
      <credito>0,00</credito>
      <saldo>78521,32</saldo>
    </conta>
    <conta>
      <numero>611511501</numero>
      <debito>0,00</debito>
      <credito>-7752,54</credito>
      <saldo>-236435,46</saldo>
    </conta>
    <conta>
      <numero>611511601</numero>
      <debito>34880,45</debito>
      <credito>0,00</credito>
      <saldo>201364,20</saldo>
    </conta>
    <conta>
      <numero>6301101</numero>
      <debito>0,00</debito>
      <credito>173,90</credito>
      <saldo>-36587,77</saldo>
    </conta>
    <conta>
      <numero>630510101</numero>
      <debito>2007600,49</debito>
      <credito>0,00</credito>
      <saldo>9237170,37</saldo>
    </conta>
    <conta>
      <numero>630540101</numero>
      <debito>1676,99</debito>
      <credito>0,00</credito>
      <saldo>104865,35</saldo>
    </conta>
    <conta>
      <numero>7501101</numero>
      <debito>46592,01</debito>
      <credito>0,00</credito>
      <saldo>318804,96</saldo>
    </conta>
    <conta>
      <numero>7501102</numero>
      <debito>84281,51</debito>
      <credito>0,00</credito>
      <saldo>569825,07</saldo>
    </conta>
  </contas></BMP>